{
    "locationName": "臺東縣",
    "geocode": "10014",
    "hazardConditions": {
        "hazards": {
            "info": {
                "language": "zh-TW",
                "phenomena": "大雨",
                "significance": "特報"
            },
            "validTime": {
                "startTime": "2016-08-13T09:33:00+08:00",
                "endTime": "2016-08-13T20:00:00+08:00"
            },
            "hazard": {
                "info": {
                    "language": "zh-TW",
                    "phenomena": "大雨",
                    "affectedAreas": {
                        "location": [
                            {
                                "locationName": "平地"
                            },
                            {
                                "locationName": "山區"
                            },
                            {
                                "locationName": "蘭嶼綠島"
                            }
                        ]
                    }
                }
            }
        }
    },
    "helper": [
        "陣雨或雷雨，早晚涼，長浪！留意坍方、落石、土石流及溪水暴漲！",
        "昨(12)日臺東地區受到熱帶低壓影響，天氣陰雨，雨量較集中在離島、達仁鄉、中~北臺東沿海和縱谷，日雨量以綠島鄉(129.5毫米)最多，其次是達仁鄉(壽卡129.0毫米)，許多地區的時雨量也都達到大雨的標準。臺東市高\/最低氣溫(28.5\/25.2)比前天(33.3\/26.5)涼很多，山區及縱谷區的高溫約25~28度，其他各地約29度，離島約27~28度。蘭嶼平均風曾達7級\/陣風10級！中~北臺東沿海海象稍不穩，浪高最大約1.2米，最大平均風3級\/陣風4級。",
        "今(13)日臺東地區凌晨迄今是陰雨的天氣，雨勢較集中在達仁鄉和長濱鄉，僅中臺東部份山區無雨中。",
        "清晨在山區及縱谷區的低溫約23~25度，其他各地的低溫約24~26度，離島則約25~26度，都與昨天接近。目前(08:00)臺東市氣溫26.0度，其他各地氣溫約在24~26度之間。",
        "中~北臺東沿海海象平穩，浪高最大約0.8米，平均風2級\/陣風3級；雷雨區風浪大。",
        "今天受到熱帶低壓的影響，早晚微涼，有陣雨或雷雨。",
        "山區、土地及道路要留意坍方、落石、土石流及溪水暴漲所帶來的影響！",
        "風浪預估：沿海(稍增強)\/外海(雷雨區風浪更大！)",
        "風向預估：中~北臺東(西)\/中~南臺東(西南-gt;東)\/外海(西南-gt;南)。",
        "舉辦金針花季系列活動的太麻里鄉，今(13)日白天天氣為:陣雨或雷雨\/體感溫度29~31度\/平均風3級(西南~東南)\/降雨機率70%！(http:\/\/www.taimali.gov.tw\/\/index_law.php?news_no=1242)"
    ],
    "recent": [
        {
            "elementName": "Wx",
            "time": [
                {
                    "startTime": "2016-08-13T12:00:00+08:00",
                    "endTime": "2016-08-13T18:00:00+08:00",
                    "parameter": {
                        "parameterName": "陰短暫陣雨或雷雨",
                        "parameterValue": "36"
                    }
                },
                {
                    "startTime": "2016-08-13T18:00:00+08:00",
                    "endTime": "2016-08-14T06:00:00+08:00",
                    "parameter": {
                        "parameterName": "多雲短暫陣雨或雷雨",
                        "parameterValue": "17"
                    }
                },
                {
                    "startTime": "2016-08-14T06:00:00+08:00",
                    "endTime": "2016-08-14T18:00:00+08:00",
                    "parameter": {
                        "parameterName": "多雲短暫陣雨或雷雨",
                        "parameterValue": "17"
                    }
                }
            ]
        },
        {
            "elementName": "MaxT",
            "time": [
                {
                    "startTime": "2016-08-13T12:00:00+08:00",
                    "endTime": "2016-08-13T18:00:00+08:00",
                    "parameter": {
                        "parameterName": "29",
                        "parameterUnit": "C"
                    }
                },
                {
                    "startTime": "2016-08-13T18:00:00+08:00",
                    "endTime": "2016-08-14T06:00:00+08:00",
                    "parameter": {
                        "parameterName": "28",
                        "parameterUnit": "C"
                    }
                },
                {
                    "startTime": "2016-08-14T06:00:00+08:00",
                    "endTime": "2016-08-14T18:00:00+08:00",
                    "parameter": {
                        "parameterName": "33",
                        "parameterUnit": "C"
                    }
                }
            ]
        },
        {
            "elementName": "MinT",
            "time": [
                {
                    "startTime": "2016-08-13T12:00:00+08:00",
                    "endTime": "2016-08-13T18:00:00+08:00",
                    "parameter": {
                        "parameterName": "28",
                        "parameterUnit": "C"
                    }
                },
                {
                    "startTime": "2016-08-13T18:00:00+08:00",
                    "endTime": "2016-08-14T06:00:00+08:00",
                    "parameter": {
                        "parameterName": "26",
                        "parameterUnit": "C"
                    }
                },
                {
                    "startTime": "2016-08-14T06:00:00+08:00",
                    "endTime": "2016-08-14T18:00:00+08:00",
                    "parameter": {
                        "parameterName": "26",
                        "parameterUnit": "C"
                    }
                }
            ]
        },
        {
            "elementName": "CI",
            "time": [
                {
                    "startTime": "2016-08-13T12:00:00+08:00",
                    "endTime": "2016-08-13T18:00:00+08:00",
                    "parameter": {
                        "parameterName": "悶熱"
                    }
                },
                {
                    "startTime": "2016-08-13T18:00:00+08:00",
                    "endTime": "2016-08-14T06:00:00+08:00",
                    "parameter": {
                        "parameterName": "舒適至悶熱"
                    }
                },
                {
                    "startTime": "2016-08-14T06:00:00+08:00",
                    "endTime": "2016-08-14T18:00:00+08:00",
                    "parameter": {
                        "parameterName": "舒適至易中暑"
                    }
                }
            ]
        },
        {
            "elementName": "PoP",
            "time": [
                {
                    "startTime": "2016-08-13T12:00:00+08:00",
                    "endTime": "2016-08-13T18:00:00+08:00",
                    "parameter": {
                        "parameterName": "50",
                        "parameterUnit": "百分比"
                    }
                },
                {
                    "startTime": "2016-08-13T18:00:00+08:00",
                    "endTime": "2016-08-14T06:00:00+08:00",
                    "parameter": {
                        "parameterName": "50",
                        "parameterUnit": "百分比"
                    }
                },
                {
                    "startTime": "2016-08-14T06:00:00+08:00",
                    "endTime": "2016-08-14T18:00:00+08:00",
                    "parameter": {
                        "parameterName": "30",
                        "parameterUnit": "百分比"
                    }
                }
            ]
        }
    ],
    "week": [
        {
            "elementName": "Wx",
            "time": [
                {
                    "startTime": "2016-08-13T12:00:00+08:00",
                    "endTime": "2016-08-13T18:00:00+08:00",
                    "parameter": {
                        "parameterName": "陰短暫陣雨或雷雨",
                        "parameterValue": "36"
                    }
                },
                {
                    "startTime": "2016-08-13T18:00:00+08:00",
                    "endTime": "2016-08-14T06:00:00+08:00",
                    "parameter": {
                        "parameterName": "多雲短暫陣雨或雷雨",
                        "parameterValue": "17"
                    }
                },
                {
                    "startTime": "2016-08-14T06:00:00+08:00",
                    "endTime": "2016-08-14T18:00:00+08:00",
                    "parameter": {
                        "parameterName": "多雲短暫陣雨或雷雨",
                        "parameterValue": "17"
                    }
                },
                {
                    "startTime": "2016-08-14T18:00:00+08:00",
                    "endTime": "2016-08-15T06:00:00+08:00",
                    "parameter": {
                        "parameterName": "多雲短暫陣雨或雷雨",
                        "parameterValue": "17"
                    }
                },
                {
                    "startTime": "2016-08-15T06:00:00+08:00",
                    "endTime": "2016-08-15T18:00:00+08:00",
                    "parameter": {
                        "parameterName": "多雲短暫陣雨或雷雨",
                        "parameterValue": "17"
                    }
                },
                {
                    "startTime": "2016-08-15T18:00:00+08:00",
                    "endTime": "2016-08-16T06:00:00+08:00",
                    "parameter": {
                        "parameterName": "多雲短暫陣雨或雷雨",
                        "parameterValue": "17"
                    }
                },
                {
                    "startTime": "2016-08-16T06:00:00+08:00",
                    "endTime": "2016-08-16T18:00:00+08:00",
                    "parameter": {
                        "parameterName": "多雲短暫陣雨或雷雨",
                        "parameterValue": "17"
                    }
                },
                {
                    "startTime": "2016-08-16T18:00:00+08:00",
                    "endTime": "2016-08-17T06:00:00+08:00",
                    "parameter": {
                        "parameterName": "多雲短暫陣雨或雷雨",
                        "parameterValue": "17"
                    }
                },
                {
                    "startTime": "2016-08-17T06:00:00+08:00",
                    "endTime": "2016-08-17T18:00:00+08:00",
                    "parameter": {
                        "parameterName": "多雲短暫陣雨或雷雨",
                        "parameterValue": "17"
                    }
                },
                {
                    "startTime": "2016-08-17T18:00:00+08:00",
                    "endTime": "2016-08-18T06:00:00+08:00",
                    "parameter": {
                        "parameterName": "多雲短暫陣雨或雷雨",
                        "parameterValue": "17"
                    }
                },
                {
                    "startTime": "2016-08-18T06:00:00+08:00",
                    "endTime": "2016-08-18T18:00:00+08:00",
                    "parameter": {
                        "parameterName": "多雲短暫陣雨或雷雨",
                        "parameterValue": "17"
                    }
                },
                {
                    "startTime": "2016-08-18T18:00:00+08:00",
                    "endTime": "2016-08-19T06:00:00+08:00",
                    "parameter": {
                        "parameterName": "多雲",
                        "parameterValue": "2"
                    }
                },
                {
                    "startTime": "2016-08-19T06:00:00+08:00",
                    "endTime": "2016-08-19T18:00:00+08:00",
                    "parameter": {
                        "parameterName": "多雲短暫陣雨或雷雨",
                        "parameterValue": "17"
                    }
                },
                {
                    "startTime": "2016-08-19T18:00:00+08:00",
                    "endTime": "2016-08-20T06:00:00+08:00",
                    "parameter": {
                        "parameterName": "多雲短暫陣雨或雷雨",
                        "parameterValue": "17"
                    }
                }
            ]
        },
        {
            "elementName": "MaxT",
            "time": [
                {
                    "startTime": "2016-08-13T12:00:00+08:00",
                    "endTime": "2016-08-13T18:00:00+08:00",
                    "parameter": {
                        "parameterName": "29",
                        "parameterUnit": "C"
                    }
                },
                {
                    "startTime": "2016-08-13T18:00:00+08:00",
                    "endTime": "2016-08-14T06:00:00+08:00",
                    "parameter": {
                        "parameterName": "28",
                        "parameterUnit": "C"
                    }
                },
                {
                    "startTime": "2016-08-14T06:00:00+08:00",
                    "endTime": "2016-08-14T18:00:00+08:00",
                    "parameter": {
                        "parameterName": "33",
                        "parameterUnit": "C"
                    }
                },
                {
                    "startTime": "2016-08-14T18:00:00+08:00",
                    "endTime": "2016-08-15T06:00:00+08:00",
                    "parameter": {
                        "parameterName": "31",
                        "parameterUnit": "C"
                    }
                },
                {
                    "startTime": "2016-08-15T06:00:00+08:00",
                    "endTime": "2016-08-15T18:00:00+08:00",
                    "parameter": {
                        "parameterName": "34",
                        "parameterUnit": "C"
                    }
                },
                {
                    "startTime": "2016-08-15T18:00:00+08:00",
                    "endTime": "2016-08-16T06:00:00+08:00",
                    "parameter": {
                        "parameterName": "31",
                        "parameterUnit": "C"
                    }
                },
                {
                    "startTime": "2016-08-16T06:00:00+08:00",
                    "endTime": "2016-08-16T18:00:00+08:00",
                    "parameter": {
                        "parameterName": "33",
                        "parameterUnit": "C"
                    }
                },
                {
                    "startTime": "2016-08-16T18:00:00+08:00",
                    "endTime": "2016-08-17T06:00:00+08:00",
                    "parameter": {
                        "parameterName": "31",
                        "parameterUnit": "C"
                    }
                },
                {
                    "startTime": "2016-08-17T06:00:00+08:00",
                    "endTime": "2016-08-17T18:00:00+08:00",
                    "parameter": {
                        "parameterName": "33",
                        "parameterUnit": "C"
                    }
                },
                {
                    "startTime": "2016-08-17T18:00:00+08:00",
                    "endTime": "2016-08-18T06:00:00+08:00",
                    "parameter": {
                        "parameterName": "31",
                        "parameterUnit": "C"
                    }
                },
                {
                    "startTime": "2016-08-18T06:00:00+08:00",
                    "endTime": "2016-08-18T18:00:00+08:00",
                    "parameter": {
                        "parameterName": "33",
                        "parameterUnit": "C"
                    }
                },
                {
                    "startTime": "2016-08-18T18:00:00+08:00",
                    "endTime": "2016-08-19T06:00:00+08:00",
                    "parameter": {
                        "parameterName": "31",
                        "parameterUnit": "C"
                    }
                },
                {
                    "startTime": "2016-08-19T06:00:00+08:00",
                    "endTime": "2016-08-19T18:00:00+08:00",
                    "parameter": {
                        "parameterName": "33",
                        "parameterUnit": "C"
                    }
                },
                {
                    "startTime": "2016-08-19T18:00:00+08:00",
                    "endTime": "2016-08-20T06:00:00+08:00",
                    "parameter": {
                        "parameterName": "31",
                        "parameterUnit": "C"
                    }
                }
            ]
        },
        {
            "elementName": "MinT",
            "time": [
                {
                    "startTime": "2016-08-13T12:00:00+08:00",
                    "endTime": "2016-08-13T18:00:00+08:00",
                    "parameter": {
                        "parameterName": "28",
                        "parameterUnit": "C"
                    }
                },
                {
                    "startTime": "2016-08-13T18:00:00+08:00",
                    "endTime": "2016-08-14T06:00:00+08:00",
                    "parameter": {
                        "parameterName": "26",
                        "parameterUnit": "C"
                    }
                },
                {
                    "startTime": "2016-08-14T06:00:00+08:00",
                    "endTime": "2016-08-14T18:00:00+08:00",
                    "parameter": {
                        "parameterName": "26",
                        "parameterUnit": "C"
                    }
                },
                {
                    "startTime": "2016-08-14T18:00:00+08:00",
                    "endTime": "2016-08-15T06:00:00+08:00",
                    "parameter": {
                        "parameterName": "27",
                        "parameterUnit": "C"
                    }
                },
                {
                    "startTime": "2016-08-15T06:00:00+08:00",
                    "endTime": "2016-08-15T18:00:00+08:00",
                    "parameter": {
                        "parameterName": "27",
                        "parameterUnit": "C"
                    }
                },
                {
                    "startTime": "2016-08-15T18:00:00+08:00",
                    "endTime": "2016-08-16T06:00:00+08:00",
                    "parameter": {
                        "parameterName": "27",
                        "parameterUnit": "C"
                    }
                },
                {
                    "startTime": "2016-08-16T06:00:00+08:00",
                    "endTime": "2016-08-16T18:00:00+08:00",
                    "parameter": {
                        "parameterName": "27",
                        "parameterUnit": "C"
                    }
                },
                {
                    "startTime": "2016-08-16T18:00:00+08:00",
                    "endTime": "2016-08-17T06:00:00+08:00",
                    "parameter": {
                        "parameterName": "27",
                        "parameterUnit": "C"
                    }
                },
                {
                    "startTime": "2016-08-17T06:00:00+08:00",
                    "endTime": "2016-08-17T18:00:00+08:00",
                    "parameter": {
                        "parameterName": "27",
                        "parameterUnit": "C"
                    }
                },
                {
                    "startTime": "2016-08-17T18:00:00+08:00",
                    "endTime": "2016-08-18T06:00:00+08:00",
                    "parameter": {
                        "parameterName": "27",
                        "parameterUnit": "C"
                    }
                },
                {
                    "startTime": "2016-08-18T06:00:00+08:00",
                    "endTime": "2016-08-18T18:00:00+08:00",
                    "parameter": {
                        "parameterName": "27",
                        "parameterUnit": "C"
                    }
                },
                {
                    "startTime": "2016-08-18T18:00:00+08:00",
                    "endTime": "2016-08-19T06:00:00+08:00",
                    "parameter": {
                        "parameterName": "27",
                        "parameterUnit": "C"
                    }
                },
                {
                    "startTime": "2016-08-19T06:00:00+08:00",
                    "endTime": "2016-08-19T18:00:00+08:00",
                    "parameter": {
                        "parameterName": "27",
                        "parameterUnit": "C"
                    }
                },
                {
                    "startTime": "2016-08-19T18:00:00+08:00",
                    "endTime": "2016-08-20T06:00:00+08:00",
                    "parameter": {
                        "parameterName": "27",
                        "parameterUnit": "C"
                    }
                }
            ]
        }
    ]
}